{"1":{"w":[{"b":"0.03","h":"0.65","c":"إِذَا","d":"idhā","e":"āَhdِiʾ"},{"b":"0.37","h":"1.1","c":"السَّمَاءُ","d":"l-samāu","e":"ُءٓāَmَّslٱ"},{"b":"3.1","h":"4.19","c":"انْفَطَرَتْ","d":"infaṭarat","e":"ْtَrَṭَfnٱ"}],"a":{"g":"When the sky breaks apart"}},"2":{"w":[{"b":"0.13","h":"0.4","c":"وَإِذَا","d":"wa-idhā","e":"āَhdِiʾَw"},{"b":"0.65","h":"1.13","c":"الْكَوَاكِبُ","d":"l-kawākibu","e":"ُbِkāَwَkْlٱ"},{"b":"1.9","h":"3.14","c":"انْتَثَرَتْ","d":"intatharat","e":"ْtَrَhtَtnٱ"}],"a":{"g":"And when the stars fall, scattering,"}},"3":{"w":[{"b":"0.07","h":"0.5","c":"وَإِذَا","d":"wa-idhā","e":"āَhdِiʾَw"},{"b":"0.57","h":"1.22","c":"الْبِحَارُ","d":"l-biḥāru","e":"ُrāَḥِbْlٱ"},{"b":"1.6","h":"2.91","c":"فُجِّرَتْ","d":"fujjirat","e":"ْtَrِّjgُf"}],"a":{"g":"And when the seas are erupted"}},"4":{"w":[{"b":"0.1","h":"0.26","c":"وَإِذَا","d":"wa-idhā","e":"āَhdِiʾَw"},{"b":"0.67","h":"1.04","c":"الْقُبُورُ","d":"l-qubūru","e":"ُrwُbُqْlٱ"},{"b":"1.7","h":"2.78","c":"بُعْثِرَتْ","d":"buʿ'thirat","e":"ْtَrِhtْʿعُb"}],"a":{"g":"And when the [contents of] graves are scattered,"}},"5":{"w":[{"b":"0.03","h":"0.3","c":"عَلِمَتْ","d":"ʿalimat","e":"ْtَmِlَʿع"},{"b":"0.81","h":"1.56","c":"نَفْسٌ","d":"nafsun","e":"ٌsْfَn"},{"b":"2.3","h":"3.35","c":"مَا","d":"mā","e":"āَّm"},{"b":"2.6","h":"4.05","c":"قَدَّمَتْ","d":"qaddamat","e":"ْtَmَّdَq"},{"b":"3.7","h":"5.67","c":"وَأَخَّرَتْ","d":"wa-akharat","e":"ْtَrَّhkَaʾَw"}],"a":{"g":"A soul will [then] know what it has put forth and kept back."}},"6":{"w":[{"b":"0.03","h":"0.65","c":"يَاأَيُّهَا","d":"yāayyuhā","e":"āَhُّyَaʾَٰٓy"},{"b":"2.6","h":"3.38","c":"الْإِنْسَانُ","d":"l-insānu","e":"ُnَٰsnِiʾْlٱ"},{"b":"4.5","h":"6.07","c":"مَا","d":"mā","e":"āَm"},{"b":"4.8","h":"6.86","c":"غَرَّكَ","d":"gharraka","e":"َkَّrَغ"},{"b":"5.8","h":"8.23","c":"بِرَبِّكَ","d":"birabbika","e":"َkِّbَrِb"},{"b":"6.8","h":"10.01","c":"الْكَرِيمِ","d":"l-karīmi","e":"ِmyِrَkْlٱ"}],"a":{"g":"O mankind, what has deceived you concerning your Lord, the Generous,"}},"7":{"w":[{"b":"0.03","h":"0.85","c":"الَّذِي","d":"alladhī","e":"àِhdَّlٱ"},{"b":"0.89","h":"2.2","c":"خَلَقَكَ","d":"khalaqaka","e":"َkَqَlَhk"},{"b":"1.7","h":"3.58","c":"فَسَوَّاكَ","d":"fasawwāka","e":"َkٰàَّwَsَf"},{"b":"3.1","h":"5.7","c":"فَعَدَلَكَ","d":"faʿadalaka","e":"َkَlَdَʿعَf"}],"a":{"g":"Who created you, proportioned you, and balanced you?"}},"8":{"w":[{"b":"0.03","h":"0.3","c":"فِي","d":"fī","e":"ٓàِf"},{"b":"0.69","h":"1.95","c":"أَيِّ","d":"ayyi","e":"ِّàَaʾ"},{"b":"2.1","h":"2.9","c":"صُورَةٍ","d":"ṣūratin","e":"ٍẗَrwُṣ"},{"b":"3.7","h":"5.39","c":"مَا","d":"mā","e":"āَّm"},{"b":"4.0","h":"6","c":"شَاءَ","d":"shāa","e":"َءٓāَhs"},{"b":"6.2","h":"8.13","c":"رَكَّبَكَ","d":"rakkabaka","e":"َkَbَّkَr"}],"a":{"g":"In whatever form He willed has He assembled you."}},"9":{"w":[{"b":"0.03","h":"0.7","c":"كَلَّا","d":"kallā","e":"āَّlَk"},{"b":"0.83","h":"1.89","c":"بَلْ","d":"bal","e":"ْlَb"},{"b":"1.2","h":"2.47","c":"تُكَذِّبُونَ","d":"tukadhibūna","e":"َnwُbِّhdَkُt"},{"b":"2.7","h":"4.82","c":"بِالدِّينِ","d":"bil-dīni","e":"ِnyِّdlٱِb"}],"a":{"g":"No! But you deny the Recompense."}},"10":{"w":[{"b":"0.04","h":"0.3","c":"وَإِنَّ","d":"wa-inna","e":"َّnِiʾَw"},{"b":"1.2","h":"1.75","c":"عَلَيْكُمْ","d":"ʿalaykum","e":"ْmُkْyَlَʿع"},{"b":"2.3","h":"3.6","c":"لَحَافِظِينَ","d":"laḥāfiẓīna","e":"َnyِẓِfَٰḥَl"}],"a":{"g":"And indeed, [appointed] over you are keepers,"}},"11":{"w":[{"b":"0.03","h":"0.4","c":"كِرَامًا","d":"kirāman","e":"āًmāَrِk"},{"b":"1.4","h":"2.34","c":"كَاتِبِينَ","d":"kātibīna","e":"َnyِbِtَٰk"}],"a":{"g":"Noble and recording;"}},"12":{"w":[{"b":"0.03","h":"0.75","c":"يَعْلَمُونَ","d":"yaʿlamūna","e":"َnwُmَlْʿعَy"},{"b":"1.1","h":"3.1","c":"مَا","d":"mā","e":"āَm"},{"b":"1.5","h":"3.3","c":"تَفْعَلُونَ","d":"tafʿalūna","e":"َnwُlَʿعْfَt"}],"a":{"g":"They know whatever you do."}},"13":{"w":[{"b":"0.03","h":"0.25","c":"إِنَّ","d":"inna","e":"َّnِiʾ"},{"b":"1.0","h":"1.67","c":"الْأَبْرَارَ","d":"l-abrāra","e":"َrāَrْbَaʾْlٱ"},{"b":"2.4","h":"3.64","c":"لَفِي","d":"lafī","e":"àِfَl"},{"b":"3.0","h":"4.79","c":"نَعِيمٍ","d":"naʿīmin","e":"ٍmyِʿعَn"}],"a":{"g":"Indeed, the righteous will be in pleasure,","ihya":"\n        <div class=\"ihya-tafsir-box\" style=\"margin-top: 15px; border-top: 1px solid #eee; padding-top: 10px;\">\n            <h5 style=\"color: #91740c; font-family: Cabin, sans-serif;\">Tafsir Al-Ihya</h5>\n            <div class=\"ihya-arabic\" style=\"font-family: IndoPak; font-size: 18px; text-align: right; margin-bottom: 10px; color: #555;\">\n                ومن امتزج بحبه حب غير الله تنعم في الآخرة بقدر حبه، إذ يمزج شرابه بقدر من شراب المقربين كما قال تعالى في الأبرار: \" إن الأبرار لفي نعيم \" ثم قال: \" يسقون من رحيق مختوم مسك وفي ذلك فليتنافس المتنافسون ومزاجه من تسنيم عيناً يشرب بها المقربون \" فإذا طاب شراب الأبرار لشوب الشراب الصرف الذي هو للمقربين.\n            </div>\n            <div class=\"ihya-english\" style=\"font-family: Arial; font-size: 14px; text-align: justify; color: #777;\">\n                Indeed, whoever mixes with his love [hubb] the love of other than Allah, he will enjoy bliss [na'eem] in the Hereafter [Akhirah] to the measure of his love, for his drink is mixed with a measure from the drink of the Brought-Near [al-Muqarrabun], just as Allah, the Exalted, said concerning the Righteous [al-Abrar]: \"Indeed, the Righteous are in bliss,\" then He said: \"They are given to drink of a pure, sealed wine, whose seal is musk—for this let the competitors compete—and whose mixture is of Tasneem, a spring from which drink those brought near.\" Thus, the drink of the Righteous is made pleasant by the admixture of the pure drink which is for those Brought Near.\n            </div>\n        </div>\n        "}},"14":{"w":[{"b":"0.04","h":"0.42","c":"وَإِنَّ","d":"wa-inna","e":"َّnِiʾَw"},{"b":"1.1","h":"1.99","c":"الْفُجَّارَ","d":"l-fujāra","e":"َrāَّjgُfْlٱ"},{"b":"2.5","h":"4.26","c":"لَفِي","d":"lafī","e":"àِfَl"},{"b":"3.1","h":"5.39","c":"جَحِيمٍ","d":"jaḥīmin","e":"ٍmyِḥَjg"}],"a":{"g":"And indeed, the wicked will be in Hellfire."}},"15":{"w":[{"b":"0.05","h":"0.6","c":"يَصْلَوْنَهَا","d":"yaṣlawnahā","e":"āَhَnْwَlْṣَy"},{"b":"1.4","h":"2.96","c":"يَوْمَ","d":"yawma","e":"َmْwَy"},{"b":"2.0","h":"4.14","c":"الدِّينِ","d":"l-dīni","e":"ِnyِّdlٱ"}],"a":{"g":"They will [enter to] burn therein on the Day of Recompense,"}},"16":{"w":[{"b":"0.03","h":"0.6","c":"وَمَا","d":"wamā","e":"āَmَw"},{"b":"0.62","h":"1.58","c":"هُمْ","d":"hum","e":"ْmُh"},{"b":"0.99","h":"2.21","c":"عَنْهَا","d":"ʿanhā","e":"āَhْnَʿع"},{"b":"1.8","h":"3.92","c":"بِغَائِبِينَ","d":"bighāibīna","e":"َnyِbِyʾٓāَغِb"}],"a":{"g":"And never therefrom will they be absent."}},"17":{"w":[{"b":"0.08","h":"0.22","c":"وَمَا","d":"wamā","e":"ٓāَmَw"},{"b":"1.7","h":"2.37","c":"أَدْرَاكَ","d":"adrāka","e":"َkٰàَrْdَaʾ"},{"b":"2.6","h":"4.2","c":"مَا","d":"mā","e":"āَm"},{"b":"3.1","h":"5.02","c":"يَوْمُ","d":"yawmu","e":"ُmْwَy"},{"b":"3.7","h":"6.07","c":"الدِّينِ","d":"l-dīni","e":"ِnyِّdlٱ"}],"a":{"g":"And what can make you know what is the Day of Recompense?"}},"18":{"w":[{"b":"0.03","h":"0.25","c":"ثُمَّ","d":"thumma","e":"َّmُht"},{"b":"0.99","h":"1.39","c":"مَا","d":"mā","e":"ٓāَm"},{"b":"2.2","h":"1.74","c":"أَدْرَاكَ","d":"adrāka","e":"َkٰàَrْdَaʾ"},{"b":"3.3","h":"5.04","c":"مَا","d":"mā","e":"āَm"},{"b":"3.8","h":"5.86","c":"يَوْمُ","d":"yawmu","e":"ُmْwَy"},{"b":"4.4","h":"6.97","c":"الدِّينِ","d":"l-dīni","e":"ِnyِّdlٱ"}],"a":{"g":"Then, what can make you know what is the Day of Recompense?"}},"19":{"w":[{"b":"0.05","h":"0.2","c":"يَوْمَ","d":"yawma","e":"َmْwَy"},{"b":"0.67","h":"1.11","c":"لَا","d":"lā","e":"āَl"},{"b":"1.0","h":"1.73","c":"تَمْلِكُ","d":"tamliku","e":"ُkِlْmَt"},{"b":"2.0","h":"3.14","c":"نَفْسٌ","d":"nafsun","e":"ٌsْfَn"},{"b":"2.8","h":"4.25","c":"لِنَفْسٍ","d":"linafsin","e":"ٍsْfَnِّl"},{"b":"4.5","h":"6.8","c":"شَيْئًا","d":"shayan","e":"āًٔـْyَhs"},{"b":"6.3","h":"10","c":"وَالْأَمْرُ","d":"wal-amru","e":"ُrْmَaʾْlٱَw"},{"b":"7.4","h":"11.5","c":"يَوْمَئِذٍ","d":"yawma-idhin","e":"ٍhdِyʾَmْwَy"},{"b":"9.5","h":"13.13","c":"لِلَّهِ","d":"lillahi","e":"ِhَّlِّl"}],"a":{"g":"It is the Day when a soul will not possess for another soul [power to do] a thing; and the command, that Day, is [entirely] with Allah."}}}